x_maes/__init__.py
x_maes-0.1.0.dist-info/LICENSE
x_maes-0.1.0.dist-info/METADATA
x_maes-0.1.0.dist-info/WHEEL
x_maes-0.1.0.dist-info/top_level.txt
x_maes-0.1.0.dist-info/RECORD
