Metadata-Version: 2.1
Name: x-maes
Version: 0.1.0
Summary: X-MAEs - Pytorch
Home-page: https://github.com/Mmhmmmmm/x-maes
Author: Jiangwei Zhao
Author-email: 2574298210@qq.com
License: MIT
Keywords: artificial intelligence,attention mechanism,transformers,mae
Platform: UNKNOWN
Classifier: Development Status :: 4 - Beta
Classifier: Intended Audience :: Developers
Classifier: Topic :: Scientific/Engineering :: Artificial Intelligence
Classifier: License :: OSI Approved :: MIT License
Classifier: Programming Language :: Python :: 3.6
License-File: LICENSE
Requires-Dist: torch (>=1.6)
Requires-Dist: einops (>=0.3)
Requires-Dist: entmax
